topic_autolabel/__init__.py
topic_autolabel/core/__init__.py
topic_autolabel/core/data_loader.py
topic_autolabel/core/labeler.py
topic_autolabel-0.1.6.dist-info/LICENSE
topic_autolabel-0.1.6.dist-info/METADATA
topic_autolabel-0.1.6.dist-info/WHEEL
topic_autolabel-0.1.6.dist-info/top_level.txt
topic_autolabel-0.1.6.dist-info/RECORD
