Metadata-Version: 2.2
Name: topic-autolabel
Version: 0.1.6
Summary: Automatic topic labeling using LLMs
Author-email: Anthony Susevski <asusevski@gmail.com>
Project-URL: Repository, https://github.com/asusevski/topic-autolabel
Requires-Python: >=3.10
License-File: LICENSE
Requires-Dist: pytest
Requires-Dist: isort
Requires-Dist: pandas
Requires-Dist: datasets
Requires-Dist: scikit-learn
Requires-Dist: instructor
Requires-Dist: torch
Requires-Dist: transformers
Requires-Dist: sentence-transformers
Requires-Dist: ollama
Provides-Extra: dev
Requires-Dist: black==24.10.0; extra == "dev"
Requires-Dist: ruff==0.8.0; extra == "dev"
Requires-Dist: isort==5.13.2; extra == "dev"
Requires-Dist: pyright==1.1.389; extra == "dev"
